README.md
setup.py
configrw/__init__.py
configrw/config.py
configrw.egg-info/PKG-INFO
configrw.egg-info/SOURCES.txt
configrw.egg-info/dependency_links.txt
configrw.egg-info/top_level.txt