Metadata-Version: 2.1
Name: configrw
Version: 1.0.0
Summary: ConfigRW is a simple reader and writer config files based on key-value or INI-structure.
Home-page: https://github.com/microcoder/configrw
Author: https://github.com/microcoder
License: MIT
Platform: UNKNOWN
